LLM_feature_gen/__init__.py
LLM_feature_gen/discover.py
LLM_feature_gen/generate.py
LLM_feature_gen/prompts/__init__.py
LLM_feature_gen/providers/__init__.py
LLM_feature_gen/providers/local_provider.py
LLM_feature_gen/providers/openai_provider.py
LLM_feature_gen/utils/__init__.py
LLM_feature_gen/utils/image.py
LLM_feature_gen/utils/text.py
LLM_feature_gen/utils/video.py
tests/test_discovery.py
tests/test_generation.py
llm_feature_gen-0.1.0.dist-info/LICENSE
llm_feature_gen-0.1.0.dist-info/METADATA
llm_feature_gen-0.1.0.dist-info/WHEEL
llm_feature_gen-0.1.0.dist-info/top_level.txt
llm_feature_gen-0.1.0.dist-info/RECORD
