Metadata-Version: 2.1
Name: llm_feature_gen
Version: 0.1.0
Summary: Feature discovery and generation utilities
Author: Julija Jeršova
License: MIT
Requires-Python: >=3.9
License-File: LICENSE
Requires-Dist: openai>=1.0.0
Requires-Dist: python-dotenv>=1.0.0
Requires-Dist: pydantic>=2
Requires-Dist: numpy>=1.26
Requires-Dist: Pillow>=10
